MANIFEST.in
README.rst
setup.py
src/ofxstatement/__init__.py
src/ofxstatement/plugins/__init__.py
src/ofxstatement/plugins/danske.py
src/ofxstatement/plugins/litas_esis.py
src/ofxstatement/plugins/swedbank.py
src/ofxstatement/plugins/tests/__init__.py
src/ofxstatement/plugins/tests/test_danske.py
src/ofxstatement/plugins/tests/test_litas_esis.py
src/ofxstatement/plugins/tests/test_swedbank.py
src/ofxstatement/plugins/tests/samples/danske.csv
src/ofxstatement/plugins/tests/samples/litas_esis.acc
src/ofxstatement/plugins/tests/samples/swedbank.csv
src/ofxstatement_lithuanian.egg-info/PKG-INFO
src/ofxstatement_lithuanian.egg-info/SOURCES.txt
src/ofxstatement_lithuanian.egg-info/dependency_links.txt
src/ofxstatement_lithuanian.egg-info/entry_points.txt
src/ofxstatement_lithuanian.egg-info/namespace_packages.txt
src/ofxstatement_lithuanian.egg-info/requires.txt
src/ofxstatement_lithuanian.egg-info/top_level.txt
src/ofxstatement_lithuanian.egg-info/zip-safe