Metadata-Version: 1.1
Name: ofxstatement-lithuanian
Version: 1.0.0
Summary: Statement parsers for banks, operatiing in Lithuania
Home-page: https://github.com/kedder/ofxstatement-lithuanian
Author: Andrey Lebedev
Author-email: andrey@lebedev.lt
License: GPLv3
Keywords: ofxstatement,lithuanian
Platform: UNKNOWN
Classifier: Development Status :: 3 - Alpha
Classifier: Programming Language :: Python :: 3
Classifier: Natural Language :: English
Classifier: Topic :: Office/Business :: Financial :: Accounting
Classifier: Topic :: Utilities
Classifier: Environment :: Console
Classifier: Operating System :: OS Independent
Classifier: License :: OSI Approved :: GNU Affero General Public License v3
